padmapper/Keyboard.py
padmapper/Mouse.py
padmapper/Padmapper.py
padmapper/Params.py
padmapper/__init__.py
padmapper/padmapper.py
padmapper/padmapper_capture.py
padmapper-1.0.1.data/data/bin/padmapper
padmapper-1.0.1.dist-info/licenses/LICENSE
padmapper-1.0.1.dist-info/METADATA
padmapper-1.0.1.dist-info/WHEEL
padmapper-1.0.1.dist-info/entry_points.txt
padmapper-1.0.1.dist-info/top_level.txt
padmapper-1.0.1.dist-info/RECORD
