Metadata-Version: 2.4
Name: Padmapper
Version: 1.0.1
Summary: Add gamepad support to Linux games that only support keyboard and/or mouse
Home-page: https://github.com/VersusBox/padmapper
Author: Mathieu Abati
License: LGPL
Classifier: Programming Language :: Python :: 3
Classifier: Operating System :: POSIX
Requires-Python: >=3.8
License-File: LICENSE
Dynamic: license-file
